password_generator/__init__.py
password_generator/generator.py
psswrdgen-2.0.0.dist-info/LICENSE
psswrdgen-2.0.0.dist-info/METADATA
psswrdgen-2.0.0.dist-info/WHEEL
psswrdgen-2.0.0.dist-info/top_level.txt
psswrdgen-2.0.0.dist-info/RECORD
