Metadata-Version: 2.1
Name: psswrdgen
Version: 2.0.0
Summary: A simple password generator library.
Home-page: https://github.com/almos05/lb_python/tree/main/lb_4/password_generator
Author: almos05
Author-email: tenderboylive3@gmail.com
Classifier: Programming Language :: Python :: 3
Classifier: License :: OSI Approved :: MIT License
Classifier: Operating System :: OS Independent
Requires-Python: >=3.6
License-File: LICENSE
